MANIFEST.in
README.md
setup.py
docs/README.md
docs/development.md
docs/jenkins-cicd.md
docs/markdown-fragmentation.md
docs/release-notes.md
docs/user-guide.md
src/mdfrag/__init__.py
src/mdfrag/__main__.py
src/mdfrag/renderer.py
src/mdfrag/splitter.py
src/mdfrag.egg-info/PKG-INFO
src/mdfrag.egg-info/SOURCES.txt
src/mdfrag.egg-info/dependency_links.txt
src/mdfrag.egg-info/requires.txt
src/mdfrag.egg-info/top_level.txt