Metadata-Version: 2.1
Name: mdfrag
Version: 0.1.0
Summary: Library for splitting markdown documents into fragments.
Home-page: UNKNOWN
Author: Network & Telecom Svcs (University of Oregon)
Author-email: rleonar7@uoregon.edu
License: MIT
Keywords: NTS,UO,Markdown,Fragmentation,Split
Platform: UNKNOWN
Classifier: Development Status :: 3 - Alpha
Classifier: Intended Audience :: Developers
Classifier: Topic :: Software Development :: Build Tools
Classifier: License :: OSI Approved :: MIT License
Classifier: Programming Language :: Python :: 3.6
Classifier: Programming Language :: Python :: 3.7
Classifier: Programming Language :: Python :: 3.8
